Metadata-Version: 2.1
Name: stardate-goddard
Version: 0.0.1
Summary: Converts date time strings into Star Trek TNG star dates.
Home-page: https://github.com/Goddard/stardate
Author: Ryein Goddard
Author-email: ryein@live.com
License: UNKNOWN
Platform: UNKNOWN
Classifier: Programming Language :: Python :: 3
Classifier: License :: OSI Approved :: MIT License
Classifier: Operating System :: OS Independent
